{
    "version": "1.35",
    "bpmnModel": {
        "iflowName": "Non PO Downpayment Request Creation",
        "__type": "iflow",
        "orientation": "Vertical",
        "isDirty": false,
        "shapes": [
            {
                "id": "Participant_1",
                "diagramId": "BPMNShape_Participant_1",
                "isDirty": false,
                "attributes": {
                    "name": "SAP_WorkflowManagement",
                    "tooltip": "",
                    "type": "Pool",
                    "flavor": "System",
                    "x": 75,
                    "y": 93,
                    "width": 100,
                    "height": 140
                }
            },
            {
                "id": "Participant_1_Lane0",
                "containedIn": "Participant_1",
                "isDirty": false,
                "attributes": {
                    "name": " ",
                    "tooltip": "",
                    "type": "Lane",
                    "flavor": "singleInstance",
                    "x": 0,
                    "y": 27,
                    "width": 100,
                    "height": 113
                }
            },
            {
                "id": "Participant_108",
                "diagramId": "BPMNShape_Participant_108",
                "isDirty": false,
                "attributes": {
                    "name": "SAPS4HANA",
                    "tooltip": "",
                    "type": "Pool",
                    "flavor": "System",
                    "x": 638,
                    "y": 464,
                    "width": 100,
                    "height": 140
                }
            },
            {
                "id": "Participant_108_Lane0",
                "containedIn": "Participant_108",
                "isDirty": false,
                "attributes": {
                    "name": " ",
                    "tooltip": "",
                    "type": "Lane",
                    "flavor": "singleInstance",
                    "x": 0,
                    "y": 27,
                    "width": 100,
                    "height": 113
                }
            },
            {
                "id": "Process_1",
                "diagramId": "BPMNShape_Participant_Process_1",
                "bpmnElementId": "Participant_Process_1",
                "isDirty": false,
                "attributes": {
                    "name": "Integration Process",
                    "tooltip": "",
                    "type": "Pool",
                    "flavor": "Process",
                    "x": 224,
                    "y": 74,
                    "width": 1054,
                    "height": 326
                }
            },
            {
                "id": "Process_1_Lane0",
                "containedIn": "Process_1",
                "isDirty": false,
                "attributes": {
                    "name": " ",
                    "tooltip": "",
                    "type": "Lane",
                    "flavor": "singleInstance",
                    "x": 0,
                    "y": 27,
                    "width": 1054,
                    "height": 299
                }
            },
            {
                "id": "EndEvent_0",
                "diagramId": "BPMNShape_EndEvent_0",
                "containedIn": "Process_1",
                "partitionedIn": "Process_1_Lane0",
                "isDirty": false,
                "attributes": {
                    "name": "End 2",
                    "tooltip": "",
                    "type": "Event",
                    "flavor": "intermediatethrow",
                    "x": 938,
                    "y": 46,
                    "width": 32,
                    "height": 32
                }
            },
            {
                "id": "CallActivity_102",
                "diagramId": "BPMNShape_CallActivity_102",
                "containedIn": "Process_1",
                "partitionedIn": "Process_1_Lane0",
                "isDirty": false,
                "attributes": {
                    "name": "XML to JSON Converter",
                    "tooltip": "",
                    "type": "Activity",
                    "flavor": "XmlToJsonConverter",
                    "x": 665,
                    "y": 32,
                    "width": 100,
                    "height": 60
                }
            },
            {
                "id": "CallActivity_113",
                "diagramId": "BPMNShape_CallActivity_113",
                "containedIn": "Process_1",
                "partitionedIn": "Process_1_Lane0",
                "isDirty": false,
                "attributes": {
                    "name": "Set Content-type",
                    "tooltip": "Modifies incoming message with additional information _newline_",
                    "type": "Activity",
                    "flavor": "Enricher",
                    "x": 802,
                    "y": 32,
                    "width": 100,
                    "height": 60
                }
            },
            {
                "id": "CallActivity_8",
                "diagramId": "BPMNShape_CallActivity_8",
                "containedIn": "Process_1",
                "partitionedIn": "Process_1_Lane0",
                "isDirty": false,
                "attributes": {
                    "name": "JSON to XML Converter",
                    "tooltip": "",
                    "type": "Activity",
                    "flavor": "JsonToXmlConverter",
                    "x": 127,
                    "y": 37,
                    "width": 100,
                    "height": 60
                }
            },
            {
                "id": "ServiceTask_105",
                "diagramId": "BPMNShape_ServiceTask_105",
                "containedIn": "Process_1",
                "partitionedIn": "Process_1_Lane0",
                "isDirty": false,
                "attributes": {
                    "name": "DPR Creation&Confirmation Response",
                    "tooltip": "",
                    "type": "Activity",
                    "flavor": "ExternalCall",
                    "x": 414,
                    "y": 37,
                    "width": 100,
                    "height": 60
                }
            },
            {
                "id": "CallActivity_121",
                "diagramId": "BPMNShape_CallActivity_121",
                "containedIn": "Process_1",
                "partitionedIn": "Process_1_Lane0",
                "isDirty": false,
                "attributes": {
                    "name": "Downpayment Confirmation",
                    "tooltip": "Name = MM_JournalEntryConfirmation_newline_Type = Mapping_newline_",
                    "type": "Activity",
                    "flavor": "MessageMapping",
                    "x": 541,
                    "y": 32,
                    "width": 100,
                    "height": 60
                }
            },
            {
                "id": "StartEvent_2",
                "diagramId": "BPMNShape_StartEvent_2",
                "containedIn": "Process_1",
                "partitionedIn": "Process_1_Lane0",
                "isDirty": false,
                "attributes": {
                    "name": "Start",
                    "tooltip": "",
                    "type": "Event",
                    "flavor": "intermediatecatch",
                    "x": 52,
                    "y": 46,
                    "width": 32,
                    "height": 32
                }
            },
            {
                "id": "SubProcess_71",
                "diagramId": "BPMNShape_SubProcess_71",
                "containedIn": "Process_1",
                "partitionedIn": "Process_1_Lane0",
                "isDirty": false,
                "attributes": {
                    "name": "Exception Subprocess 1",
                    "tooltip": "",
                    "type": "subProcess",
                    "flavor": "ErrorEventSubProcessTemplate",
                    "x": 563,
                    "y": 126,
                    "width": 384,
                    "height": 141
                }
            },
            {
                "id": "StartEvent_72",
                "diagramId": "BPMNShape_StartEvent_72",
                "containedIn": "Process_1",
                "partitionedIn": "SubProcess_71",
                "isDirty": false,
                "attributes": {
                    "name": "Error Start 1",
                    "tooltip": "",
                    "type": "Event",
                    "flavor": "errorStart",
                    "x": 85,
                    "y": 45,
                    "width": 32,
                    "height": 32
                }
            },
            {
                "id": "EndEvent_83",
                "diagramId": "BPMNShape_EndEvent_83",
                "containedIn": "Process_1",
                "partitionedIn": "SubProcess_71",
                "isDirty": false,
                "attributes": {
                    "name": "End 1",
                    "tooltip": "",
                    "type": "Event",
                    "flavor": "intermediatethrow",
                    "x": 290,
                    "y": 44,
                    "width": 32,
                    "height": 32
                }
            },
            {
                "id": "CallActivity_119",
                "diagramId": "BPMNShape_CallActivity_119",
                "containedIn": "Process_1",
                "partitionedIn": "SubProcess_71",
                "isDirty": false,
                "attributes": {
                    "name": "Error Response",
                    "tooltip": "Modifies incoming message with additional information _newline_",
                    "type": "Activity",
                    "flavor": "Enricher",
                    "x": 152,
                    "y": 35,
                    "width": 100,
                    "height": 60
                }
            },
            {
                "id": "CallActivity_11",
                "diagramId": "BPMNShape_CallActivity_11",
                "containedIn": "Process_1",
                "partitionedIn": "Process_1_Lane0",
                "isDirty": false,
                "attributes": {
                    "name": "Downpayment Request Mapping",
                    "tooltip": "Name = Workflow_to_S4Hana_newline_Type = Mapping_newline_",
                    "type": "Activity",
                    "flavor": "MessageMapping",
                    "x": 271,
                    "y": 37,
                    "width": 100,
                    "height": 60
                }
            }
        ],
        "connectors": [
            {
                "source": "Participant_1",
                "target": "StartEvent_2",
                "id": "MessageFlow_4",
                "isDirty": false,
                "diagramId": "BPMNEdge_MessageFlow_4",
                "sourceDiagramElement": "BPMNShape_Participant_1",
                "targetDiagramElement": "BPMNShape_StartEvent_2",
                "attributes": {
                    "name": "HTTPS",
                    "tooltip": "Name = HTTPS_newline_Adapter Type = HTTPS_newline_Transport Protocol =HTTPS_newline_Message Protocol = None_newline_",
                    "type": "Connection",
                    "flavor": "message",
                    "x": 0,
                    "y": 0,
                    "width": 0,
                    "height": 0
                }
            },
            {
                "source": "ServiceTask_105",
                "target": "Participant_108",
                "id": "MessageFlow_109",
                "isDirty": false,
                "diagramId": "BPMNEdge_MessageFlow_109",
                "sourceDiagramElement": "BPMNShape_ServiceTask_105",
                "targetDiagramElement": "BPMNShape_Participant_108",
                "attributes": {
                    "name": "SOAP",
                    "tooltip": "Name = SOAP_newline_Adapter Type = SOAP_newline_Transport Protocol = HTTPS_newline_Message Protocol = SOAP 1.x_newline_",
                    "type": "Connection",
                    "flavor": "message",
                    "x": 0,
                    "y": 0,
                    "width": 0,
                    "height": 0
                }
            },
            {
                "source": "CallActivity_102",
                "target": "CallActivity_113",
                "id": "SequenceFlow_111",
                "isDirty": false,
                "diagramId": "BPMNEdge_SequenceFlow_111",
                "sourceDiagramElement": "BPMNShape_CallActivity_102",
                "targetDiagramElement": "BPMNShape_CallActivity_113",
                "attributes": {
                    "name": "",
                    "type": "Connection",
                    "flavor": "none",
                    "x": 0,
                    "y": 0,
                    "width": 0,
                    "height": 0
                }
            },
            {
                "source": "CallActivity_113",
                "target": "EndEvent_0",
                "id": "SequenceFlow_114",
                "isDirty": false,
                "diagramId": "BPMNEdge_SequenceFlow_114",
                "sourceDiagramElement": "BPMNShape_CallActivity_113",
                "targetDiagramElement": "BPMNShape_EndEvent_0",
                "attributes": {
                    "name": "",
                    "type": "Connection",
                    "flavor": "none",
                    "x": 0,
                    "y": 0,
                    "width": 0,
                    "height": 0
                }
            },
            {
                "source": "CallActivity_8",
                "target": "CallActivity_11",
                "id": "SequenceFlow_118",
                "isDirty": false,
                "diagramId": "BPMNEdge_SequenceFlow_118",
                "sourceDiagramElement": "BPMNShape_CallActivity_8",
                "targetDiagramElement": "BPMNShape_CallActivity_11",
                "attributes": {
                    "name": "",
                    "type": "Connection",
                    "flavor": "none",
                    "x": 0,
                    "y": 0,
                    "width": 0,
                    "height": 0
                }
            },
            {
                "source": "ServiceTask_105",
                "target": "CallActivity_121",
                "id": "SequenceFlow_110",
                "isDirty": false,
                "diagramId": "BPMNEdge_SequenceFlow_110",
                "sourceDiagramElement": "BPMNShape_ServiceTask_105",
                "targetDiagramElement": "BPMNShape_CallActivity_121",
                "attributes": {
                    "name": "",
                    "type": "Connection",
                    "flavor": "none",
                    "x": 0,
                    "y": 0,
                    "width": 0,
                    "height": 0
                }
            },
            {
                "source": "CallActivity_121",
                "target": "CallActivity_102",
                "id": "SequenceFlow_122",
                "isDirty": false,
                "diagramId": "BPMNEdge_SequenceFlow_122",
                "sourceDiagramElement": "BPMNShape_CallActivity_121",
                "targetDiagramElement": "BPMNShape_CallActivity_102",
                "attributes": {
                    "name": "",
                    "type": "Connection",
                    "flavor": "none",
                    "x": 0,
                    "y": 0,
                    "width": 0,
                    "height": 0
                }
            },
            {
                "source": "StartEvent_2",
                "target": "CallActivity_8",
                "id": "SequenceFlow_116",
                "isDirty": false,
                "diagramId": "BPMNEdge_SequenceFlow_116",
                "sourceDiagramElement": "BPMNShape_StartEvent_2",
                "targetDiagramElement": "BPMNShape_CallActivity_8",
                "attributes": {
                    "name": "",
                    "type": "Connection",
                    "flavor": "none",
                    "x": 0,
                    "y": 0,
                    "width": 0,
                    "height": 0
                }
            },
            {
                "source": "StartEvent_72",
                "target": "CallActivity_119",
                "id": "SequenceFlow_74",
                "isDirty": false,
                "diagramId": "BPMNEdge_SequenceFlow_74",
                "sourceDiagramElement": "BPMNShape_StartEvent_72",
                "targetDiagramElement": "BPMNShape_CallActivity_119",
                "attributes": {
                    "name": "",
                    "type": "Connection",
                    "flavor": "none",
                    "x": 0,
                    "y": 0,
                    "width": 0,
                    "height": 0
                }
            },
            {
                "source": "CallActivity_119",
                "target": "EndEvent_83",
                "id": "SequenceFlow_120",
                "isDirty": false,
                "diagramId": "BPMNEdge_SequenceFlow_120",
                "sourceDiagramElement": "BPMNShape_CallActivity_119",
                "targetDiagramElement": "BPMNShape_EndEvent_83",
                "attributes": {
                    "name": "",
                    "type": "Connection",
                    "flavor": "none",
                    "x": 0,
                    "y": 0,
                    "width": 0,
                    "height": 0
                }
            },
            {
                "source": "CallActivity_11",
                "target": "ServiceTask_105",
                "id": "SequenceFlow_90",
                "isDirty": false,
                "diagramId": "BPMNEdge_SequenceFlow_90",
                "sourceDiagramElement": "BPMNShape_CallActivity_11",
                "targetDiagramElement": "BPMNShape_ServiceTask_105",
                "attributes": {
                    "name": "",
                    "type": "Connection",
                    "flavor": "none",
                    "x": 0,
                    "y": 0,
                    "width": 0,
                    "height": 0
                }
            }
        ]
    },
    "propertyViewModel": {
        "defaultIntegrationFlowModel": {
            "ITYPE": "DEFAULT_INTEGRATION_FLOW",
            "id": "Collobaration_1",
            "name": "Collobaration_1",
            "componentVersion": "1.1",
            "displayName": "Integration Flow",
            "hashedMetadataURI": "Y3R5cGU6OklGbG93VmFyaWFudC9jbmFtZTo6SUZsb3dDb25maWd1cmF0aW9uL3ZlcnNpb246OjEuMS4xNw==",
            "metadataURI": "ctype::IFlowVariant/cname::IFlowConfiguration/version::1.1.17",
            "allAttributes": {
                "namespaceMapping": {
                    "value": "xmlns:p1=http://sap.com/xi/SAPSCORE/SFIN,;xmlns:p2=http://sap.com/xi/SAPSCORE/SFIN",
                    "defaultValue": "",
                    "key": "",
                    "isPersisted": true
                },
                "allowedHeaderList": {
                    "value": "",
                    "defaultValue": "",
                    "key": "",
                    "isPersisted": true
                },
                "Description": {
                    "value": "",
                    "defaultValue": "",
                    "key": "",
                    "isPersisted": false
                },
                "httpSessionHandling": {
                    "value": "None",
                    "defaultValue": "None",
                    "key": "SessionReuse",
                    "additionalMetadata": {
                        "isCombobox": "true"
                    },
                    "isPersisted": true
                },
                "ServerTrace": {
                    "value": "false",
                    "defaultValue": "",
                    "key": "",
                    "isPersisted": true
                },
                "returnExceptionToSender": {
                    "value": "false",
                    "defaultValue": "",
                    "key": "",
                    "isPersisted": true
                },
                "log": {
                    "value": "All events",
                    "defaultValue": "",
                    "key": "",
                    "isPersisted": true
                },
                "name": {
                    "value": "Supplier Down Payment Request Creation and Confirmation",
                    "defaultValue": "",
                    "key": ""
                },
                "bundleId": {
                    "value": "Supplier_Downpayment_Request_Creation_and_Confirmation",
                    "defaultValue": "",
                    "key": ""
                },
                "productProfiles": {
                    "value": "iflmap",
                    "defaultValue": "",
                    "key": ""
                }
            },
            "allTableAttributes": {},
            "properties": {},
            "technicalCapabilities": {
                "$profile.isCapabilitySupported(com.sap.it.capability.igwpro.debug-trace-configuration:Debug Trace Configuration)": "false",
                "$profile.isCapabilitySupported(com.sap.it.capability.igwpro.mpl-log-level-configuration:Mpl Log Level Configuration)": "false"
            },
            "uiControlCapabilities": {
                "$action.enableAlwaysWithRoleCheck()": "WebToolingWorkspace.Write"
            }
        },
        "listOfSenderModel": [
            {
                "ITYPE": "SENDER",
                "id": "Participant_1",
                "name": {
                    "value": "SAP_WorkflowManagement",
                    "defaultValue": "",
                    "key": ""
                },
                "type": {
                    "value": "EndpointSender",
                    "defaultValue": "",
                    "key": ""
                },
                "isAuthenticationRelevant": false,
                "systemSenderAuth": [],
                "enableBasicAuthentication": {
                    "value": false,
                    "defaultValue": false,
                    "key": "",
                    "iflowBooleanType": "BOOL_TYPE_STRING"
                },
                "metadataURI": "ctype::FlowstepVariant/cname::System",
                "hashedMetadataURI": "Y3R5cGU6OkZsb3dzdGVwVmFyaWFudC9jbmFtZTo6U3lzdGVt"
            }
        ],
        "listOfReceiverModel": [
            {
                "ITYPE": "RECEIVER",
                "id": "Participant_108",
                "name": {
                    "value": "SAPS4HANA",
                    "defaultValue": "",
                    "key": ""
                },
                "type": {
                    "value": "EndpointRecevier",
                    "defaultValue": "",
                    "key": ""
                },
                "systemType": {
                    "value": "System",
                    "defaultValue": "",
                    "key": ""
                },
                "typeIDs": [
                    {
                        "typeId": ""
                    }
                ],
                "metadataURI": "ctype::FlowstepVariant/cname::System",
                "hashedMetadataURI": "Y3R5cGU6OkZsb3dzdGVwVmFyaWFudC9jbmFtZTo6U3lzdGVt"
            }
        ],
        "listOfDefaultRouteModel": [],
        "listOfDefaultChannelModel": [
            {
                "ITYPE": "DEFAULT_CHANNEL",
                "id": "MessageFlow_4",
                "componentVersion": "1.4",
                "name": {
                    "value": "HTTPS",
                    "defaultValue": "",
                    "key": ""
                },
                "direction": {
                    "value": "Sender",
                    "defaultValue": "",
                    "key": ""
                },
                "system": {
                    "value": "SAP_WorkflowManagement",
                    "defaultValue": "",
                    "key": ""
                },
                "description": {
                    "value": "",
                    "defaultValue": "",
                    "key": ""
                },
                "adapterType": {
                    "value": "HTTPS",
                    "defaultValue": "",
                    "key": ""
                },
                "transportProtocol": {
                    "value": "HTTPS",
                    "defaultValue": "",
                    "key": ""
                },
                "messageProtocol": {
                    "value": "None",
                    "defaultValue": "",
                    "key": ""
                },
                "componentNS": {
                    "value": "sap",
                    "defaultValue": "",
                    "key": ""
                },
                "componentSWCVId": {
                    "value": "1.4.1",
                    "defaultValue": "",
                    "key": ""
                },
                "componentSWCVName": {
                    "value": "external",
                    "defaultValue": "",
                    "key": ""
                },
                "transportProtocolVersion": {
                    "value": "1.4.1",
                    "defaultValue": "",
                    "key": ""
                },
                "messageProtocolVersion": {
                    "value": "1.4.1",
                    "defaultValue": "",
                    "key": ""
                },
                "transportProtocolDisplayName": {
                    "value": "HTTPS",
                    "defaultValue": "",
                    "key": ""
                },
                "messageProtocolDisplayName": {
                    "value": "None",
                    "defaultValue": "",
                    "key": ""
                },
                "adapterDisplayName": {
                    "value": "HTTPS",
                    "defaultValue": "",
                    "key": ""
                },
                "vendor": {
                    "value": "",
                    "defaultValue": "",
                    "key": ""
                },
                "allAttributes": {
                    "maximumBodySize": {
                        "value": "40",
                        "defaultValue": "40",
                        "key": "BodySize",
                        "additionalMetadata": {},
                        "isPersisted": true
                    },
                    "xsrfProtection": {
                        "value": "0",
                        "defaultValue": "0",
                        "key": "CSRF",
                        "additionalMetadata": {
                            "isCombobox": "false"
                        },
                        "isPersisted": true
                    },
                    "userRole": {
                        "value": "ESBMessaging.send",
                        "defaultValue": "ESBMessaging.send",
                        "key": "UserRole",
                        "additionalMetadata": {},
                        "isPersisted": true
                    },
                    "urlPath": {
                        "value": "/SupplierDPRfromWorkflow",
                        "defaultValue": "",
                        "key": "",
                        "isPersisted": true
                    },
                    "senderAuthType": {
                        "value": "RoleBased",
                        "defaultValue": "",
                        "key": "",
                        "isPersisted": true
                    }
                },
                "allTableAttributes": {
                    "clientCertificates": {
                        "value": [],
                        "isPersisted": true
                    }
                },
                "technicalCapabilities": {},
                "properties": {},
                "hashedMetadataURI": "Y3R5cGU6OkFkYXB0ZXJWYXJpYW50L2NuYW1lOjpzYXA6SFRUUFMvdHA6OkhUVFBTL21wOjpOb25lL2RpcmVjdGlvbjo6U2VuZGVyL3ZlcnNpb246OjEuNC4x",
                "metadataURI": "ctype::AdapterVariant/cname::sap:HTTPS/tp::HTTPS/mp::None/direction::Sender/version::1.4.1",
                "systemId": "Participant_1"
            },
            {
                "ITYPE": "DEFAULT_CHANNEL",
                "id": "MessageFlow_109",
                "componentVersion": "1.10",
                "name": {
                    "value": "SOAP",
                    "defaultValue": "",
                    "key": ""
                },
                "direction": {
                    "value": "Receiver",
                    "defaultValue": "",
                    "key": ""
                },
                "system": {
                    "value": "SAPS4HANA",
                    "defaultValue": "",
                    "key": ""
                },
                "description": {
                    "value": "",
                    "defaultValue": "",
                    "key": ""
                },
                "adapterType": {
                    "value": "SOAP",
                    "defaultValue": "",
                    "key": ""
                },
                "transportProtocol": {
                    "value": "HTTP",
                    "defaultValue": "",
                    "key": ""
                },
                "messageProtocol": {
                    "value": "SOAP 1.x",
                    "defaultValue": "",
                    "key": ""
                },
                "componentNS": {
                    "value": "sap",
                    "defaultValue": "",
                    "key": ""
                },
                "componentSWCVId": {
                    "value": "1.10.0",
                    "defaultValue": "",
                    "key": ""
                },
                "componentSWCVName": {
                    "value": "external",
                    "defaultValue": "",
                    "key": ""
                },
                "transportProtocolVersion": {
                    "value": "1.10.0",
                    "defaultValue": "",
                    "key": ""
                },
                "messageProtocolVersion": {
                    "value": "1.10.0",
                    "defaultValue": "",
                    "key": ""
                },
                "transportProtocolDisplayName": {
                    "value": "HTTPS",
                    "defaultValue": "",
                    "key": ""
                },
                "messageProtocolDisplayName": {
                    "value": "SOAP 1.x",
                    "defaultValue": "",
                    "key": ""
                },
                "adapterDisplayName": {
                    "value": "SOAP",
                    "defaultValue": "",
                    "key": ""
                },
                "vendor": {
                    "value": "",
                    "defaultValue": "",
                    "key": ""
                },
                "allAttributes": {
                    "cleanupHeaders": {
                        "value": "0",
                        "defaultValue": "",
                        "key": "",
                        "isPersisted": true
                    },
                    "WsdlUserNameTokenCredentialName": {
                        "value": "",
                        "defaultValue": "",
                        "key": "",
                        "isPersisted": true
                    },
                    "WSSecurityType_outbound": {
                        "value": "SignMessage",
                        "defaultValue": "",
                        "key": "",
                        "isPersisted": true
                    },
                    "InitiatorTokenIncludeStrategy_outbound": {
                        "value": "AlwaysToRecipient",
                        "defaultValue": "",
                        "key": "",
                        "isPersisted": true
                    },
                    "SetTimeStamp": {
                        "value": "0",
                        "defaultValue": "",
                        "key": "",
                        "isPersisted": true
                    },
                    "privateKeyAlias": {
                        "value": "",
                        "defaultValue": "",
                        "key": "",
                        "isPersisted": true
                    },
                    "location_id": {
                        "value": "",
                        "defaultValue": "",
                        "key": "",
                        "isPersisted": true
                    },
                    "UserNameTokenOption": {
                        "value": "None",
                        "defaultValue": "",
                        "key": "",
                        "isPersisted": true
                    },
                    "proxyPort": {
                        "value": "",
                        "defaultValue": "",
                        "key": "",
                        "isPersisted": true
                    },
                    "WSSecurity_SignatureAlgorithm": {
                        "value": "SHA1",
                        "defaultValue": "",
                        "key": "",
                        "isPersisted": true
                    },
                    "PublicKeyAliasEncryption_wsdl": {
                        "value": "",
                        "defaultValue": "",
                        "key": "",
                        "isPersisted": true
                    },
                    "recipientX509TokenAssertion": {
                        "value": "WssX509V3Token10",
                        "defaultValue": "",
                        "key": "",
                        "isPersisted": true
                    },
                    "soapWsdlURL": {
                        "value": "",
                        "defaultValue": "",
                        "key": "",
                        "isPersisted": true
                    },
                    "CompressMessage": {
                        "value": "0",
                        "defaultValue": "",
                        "key": "",
                        "isPersisted": true
                    },
                    "sendHttpResponseCode": {
                        "value": "0",
                        "defaultValue": "",
                        "key": "",
                        "isPersisted": true
                    },
                    "soapServiceName": {
                        "value": "",
                        "defaultValue": "",
                        "key": "",
                        "isPersisted": true
                    },
                    "requestTimeout": {
                        "value": "60000",
                        "defaultValue": "60000",
                        "key": "Timeout",
                        "additionalMetadata": {},
                        "isPersisted": true
                    },
                    "authentication": {
                        "value": "Basic",
                        "defaultValue": "Basic",
                        "key": "S4Authentication",
                        "additionalMetadata": {
                            "isCombobox": "true"
                        },
                        "isPersisted": true
                    },
                    "PrivateKeyAliasSigning": {
                        "value": "",
                        "defaultValue": "",
                        "key": "",
                        "isPersisted": true
                    },
                    "X509TokenAssertion": {
                        "value": "WssX509V3Token10",
                        "defaultValue": "",
                        "key": "",
                        "isPersisted": true
                    },
                    "address": {
                        "value": "{{S4Hostname}}/sap/bc/srt/scs_ext/sap/journalentrycreaterequestconfi",
                        "defaultValue": "{{S4Hostname}}/sap/bc/srt/scs_ext/sap/journalentrycreaterequestconfi",
                        "key": "",
                        "partialParameters": [
                            {
                                "value": "https://s4hana.api.host",
                                "defaultValue": "https://s4hana.api.host",
                                "key": "S4Hostname",
                                "additionalMetadata": {}
                            }
                        ],
                        "isPersisted": true
                    },
                    "SenderBasicSecurityProfileCompliant_wsdl": {
                        "value": "1",
                        "defaultValue": "",
                        "key": "",
                        "isPersisted": true
                    },
                    "allowChunking": {
                        "value": "0",
                        "defaultValue": "",
                        "key": "",
                        "isPersisted": true
                    },
                    "proxyType": {
                        "value": "default",
                        "defaultValue": "default",
                        "key": "proxy",
                        "additionalMetadata": {
                            "isCombobox": "true"
                        },
                        "isPersisted": true
                    },
                    "soapWsdlPortName": {
                        "value": "",
                        "defaultValue": "",
                        "key": "",
                        "isPersisted": true
                    },
                    "operationName": {
                        "value": "",
                        "defaultValue": "",
                        "key": "",
                        "isPersisted": true
                    },
                    "PrivateKeyAliasSigning_wsdl": {
                        "value": "",
                        "defaultValue": "",
                        "key": "",
                        "isPersisted": true
                    },
                    "proxyHost": {
                        "value": "",
                        "defaultValue": "",
                        "key": "",
                        "isPersisted": true
                    },
                    "PublicKeyAliasEncryption": {
                        "value": "",
                        "defaultValue": "",
                        "key": "",
                        "isPersisted": true
                    },
                    "WSSecurity_outbound": {
                        "value": "None",
                        "defaultValue": "",
                        "key": "",
                        "isPersisted": true
                    },
                    "SenderBasicSecurityProfileCompliant": {
                        "value": "1",
                        "defaultValue": "",
                        "key": "",
                        "isPersisted": true
                    },
                    "RecipientTokenIncludeStrategy": {
                        "value": "Never",
                        "defaultValue": "",
                        "key": "",
                        "isPersisted": true
                    },
                    "UserNameTokenCredentialName": {
                        "value": "",
                        "defaultValue": "",
                        "key": "",
                        "isPersisted": true
                    },
                    "AlgorithmSuiteAssertion": {
                        "value": "Basic128Rsa15",
                        "defaultValue": "",
                        "key": "",
                        "isPersisted": true
                    },
                    "credentialName": {
                        "value": "S4HANA",
                        "defaultValue": "S4HANA",
                        "key": "S4Credential",
                        "additionalMetadata": {},
                        "isPersisted": true
                    },
                    "Layout_outbound": {
                        "value": "Strict",
                        "defaultValue": "",
                        "key": "",
                        "isPersisted": true
                    }
                },
                "allTableAttributes": {},
                "technicalCapabilities": {
                    "$profile.isCapabilitySupported(com.sap.it.capability.igwpro.manual-proxy:Manual Proxy Connectivity)": "false"
                },
                "properties": {},
                "hashedMetadataURI": "Y3R5cGU6OkFkYXB0ZXJWYXJpYW50L2NuYW1lOjpzYXA6U09BUC90cDo6SFRUUC9tcDo6U09BUCAxLngvZGlyZWN0aW9uOjpSZWNlaXZlci92ZXJzaW9uOjoxLjEwLjA=",
                "metadataURI": "ctype::AdapterVariant/cname::sap:SOAP/tp::HTTP/mp::SOAP 1.x/direction::Receiver/version::1.10.0",
                "systemId": "Participant_108"
            }
        ],
        "listOfDefaultFlowElementModel": [
            {
                "id": "EndEvent_0",
                "name": "End 2",
                "componentVersion": "1.1",
                "activityType": "",
                "displayName": "End Message",
                "ITYPE": "DEFAULT_FLOWSTEP",
                "allAttributes": {},
                "allTableAttributes": {},
                "properties": {
                    "flowstepGeneralTabRequired": "true"
                },
                "hashedMetadataURI": "Y3R5cGU6OkZsb3dzdGVwVmFyaWFudC9jbmFtZTo6TWVzc2FnZUVuZEV2ZW50L3ZlcnNpb246OjEuMS4w",
                "metadataURI": "ctype::FlowstepVariant/cname::MessageEndEvent/version::1.1.0",
                "technicalCapabilities": {}
            },
            {
                "id": "CallActivity_102",
                "name": "XML to JSON Converter",
                "componentVersion": "1.0",
                "activityType": "XmlToJsonConverter",
                "displayName": "XML To JSON Converter",
                "ITYPE": "DEFAULT_FLOWSTEP",
                "allAttributes": {
                    "xmlJsonUseStreaming": {
                        "value": "false",
                        "defaultValue": "",
                        "key": "",
                        "isPersisted": true
                    },
                    "xmlJsonSuppressRootElement": {
                        "value": "true",
                        "defaultValue": "",
                        "key": "",
                        "isPersisted": true
                    },
                    "jsonOutputEncoding": {
                        "value": "",
                        "defaultValue": "",
                        "key": "",
                        "isPersisted": true
                    },
                    "xmlJsonConvertAllElements": {
                        "value": "specific",
                        "defaultValue": "",
                        "key": "",
                        "isPersisted": true
                    },
                    "useNamespaces": {
                        "value": "true",
                        "defaultValue": "",
                        "key": "",
                        "isPersisted": true
                    },
                    "jsonNamespaceSeparator": {
                        "value": ":",
                        "defaultValue": "",
                        "key": "",
                        "isPersisted": true
                    }
                },
                "allTableAttributes": {
                    "xmlJsonPathTable": {
                        "value": [],
                        "isPersisted": true
                    },
                    "jsonNamespaceMapping": {
                        "value": [],
                        "isPersisted": true
                    }
                },
                "properties": {
                    "flowstepGeneralTabRequired": "true"
                },
                "hashedMetadataURI": "Y3R5cGU6OkZsb3dzdGVwVmFyaWFudC9jbmFtZTo6WG1sVG9Kc29uQ29udmVydGVyL3ZlcnNpb246OjEuMC42",
                "metadataURI": "ctype::FlowstepVariant/cname::XmlToJsonConverter/version::1.0.6",
                "technicalCapabilities": {}
            },
            {
                "id": "CallActivity_113",
                "name": "Set Content-type",
                "componentVersion": "1.5",
                "activityType": "Enricher",
                "displayName": "Content Modifier",
                "ITYPE": "DEFAULT_FLOWSTEP",
                "allAttributes": {
                    "bodyType": {
                        "value": "expression",
                        "defaultValue": "",
                        "key": "",
                        "isPersisted": true
                    },
                    "wrapContent": {
                        "value": "",
                        "defaultValue": "",
                        "key": "",
                        "isPersisted": true
                    }
                },
                "allTableAttributes": {
                    "propertyTable": {
                        "value": [
                            {
                                "Action": {
                                    "value": "Create",
                                    "defaultValue": "",
                                    "key": ""
                                },
                                "Type": {
                                    "value": "constant",
                                    "defaultValue": "",
                                    "key": ""
                                },
                                "Value": {
                                    "value": "${in.body}",
                                    "defaultValue": "",
                                    "key": ""
                                },
                                "Default": {
                                    "value": "",
                                    "defaultValue": "",
                                    "key": ""
                                },
                                "Name": {
                                    "value": "Payload",
                                    "defaultValue": "",
                                    "key": ""
                                },
                                "Datatype": {
                                    "value": "",
                                    "defaultValue": "",
                                    "key": ""
                                }
                            }
                        ],
                        "isPersisted": true
                    },
                    "headerTable": {
                        "value": [
                            {
                                "Action": {
                                    "value": "Create",
                                    "defaultValue": "",
                                    "key": ""
                                },
                                "Type": {
                                    "value": "constant",
                                    "defaultValue": "",
                                    "key": ""
                                },
                                "Value": {
                                    "value": "application/json",
                                    "defaultValue": "",
                                    "key": ""
                                },
                                "Default": {
                                    "value": "",
                                    "defaultValue": "",
                                    "key": ""
                                },
                                "Name": {
                                    "value": "Content-Type",
                                    "defaultValue": "",
                                    "key": ""
                                },
                                "Datatype": {
                                    "value": "",
                                    "defaultValue": "",
                                    "key": ""
                                }
                            }
                        ],
                        "isPersisted": true
                    }
                },
                "properties": {
                    "flowstepGeneralTabRequired": "true"
                },
                "hashedMetadataURI": "Y3R5cGU6OkZsb3dzdGVwVmFyaWFudC9jbmFtZTo6RW5yaWNoZXIvdmVyc2lvbjo6MS41LjA=",
                "metadataURI": "ctype::FlowstepVariant/cname::Enricher/version::1.5.0",
                "technicalCapabilities": {}
            },
            {
                "id": "CallActivity_8",
                "name": "JSON to XML Converter",
                "componentVersion": "1.1",
                "activityType": "JsonToXmlConverter",
                "displayName": "JSON To XML Converter",
                "ITYPE": "DEFAULT_FLOWSTEP",
                "allAttributes": {
                    "additionalRootElementName": {
                        "value": "root",
                        "defaultValue": "",
                        "key": "",
                        "isPersisted": true
                    },
                    "useNamespaces": {
                        "value": "true",
                        "defaultValue": "",
                        "key": "",
                        "isPersisted": true
                    },
                    "addXMLRootElement": {
                        "value": "false",
                        "defaultValue": "",
                        "key": "",
                        "isPersisted": true
                    },
                    "additionalRootElementNamespace": {
                        "value": "",
                        "defaultValue": "",
                        "key": "",
                        "isPersisted": true
                    },
                    "jsonNamespaceSeparator": {
                        "value": ":",
                        "defaultValue": "",
                        "key": "",
                        "isPersisted": true
                    }
                },
                "allTableAttributes": {
                    "jsonNamespaceMapping": {
                        "value": [],
                        "isPersisted": true
                    }
                },
                "properties": {
                    "flowstepGeneralTabRequired": "true"
                },
                "hashedMetadataURI": "Y3R5cGU6OkZsb3dzdGVwVmFyaWFudC9jbmFtZTo6SnNvblRvWG1sQ29udmVydGVyL3ZlcnNpb246OjEuMS4x",
                "metadataURI": "ctype::FlowstepVariant/cname::JsonToXmlConverter/version::1.1.1",
                "technicalCapabilities": {}
            },
            {
                "id": "ServiceTask_105",
                "name": "DPR Creation&Confirmation Response",
                "componentVersion": "1.0",
                "activityType": "ExternalCall",
                "displayName": "Request Reply",
                "ITYPE": "DEFAULT_FLOWSTEP",
                "allAttributes": {},
                "allTableAttributes": {},
                "properties": {
                    "flowstepGeneralTabRequired": "true"
                },
                "hashedMetadataURI": "Y3R5cGU6OkZsb3dzdGVwVmFyaWFudC9jbmFtZTo6RXh0ZXJuYWxDYWxsL3ZlcnNpb246OjEuMC40",
                "metadataURI": "ctype::FlowstepVariant/cname::ExternalCall/version::1.0.4",
                "technicalCapabilities": {}
            },
            {
                "id": "CallActivity_121",
                "name": "Downpayment Confirmation",
                "componentVersion": "1.2",
                "activityType": "MessageMapping",
                "displayName": "Message Mapping",
                "ITYPE": "DEFAULT_FLOWSTEP",
                "allAttributes": {
                    "mappinguri": {
                        "value": "dir://mmap/src/main/resources/mapping/MM_JournalEntryConfirmation.mmap",
                        "defaultValue": "",
                        "key": "",
                        "isPersisted": true
                    },
                    "mappingname": {
                        "value": "MM_JournalEntryConfirmation",
                        "defaultValue": "",
                        "key": "",
                        "isPersisted": true
                    },
                    "mappingpath": {
                        "value": "/MM_JournalEntryConfirmation.mmap",
                        "defaultValue": "",
                        "key": "",
                        "isPersisted": true
                    },
                    "messageMappingBundleId": {
                        "value": "",
                        "defaultValue": "",
                        "key": "",
                        "isPersisted": true
                    }
                },
                "allTableAttributes": {},
                "properties": {
                    "flowstepGeneralTabRequired": "true"
                },
                "hashedMetadataURI": "Y3R5cGU6OkZsb3dzdGVwVmFyaWFudC9jbmFtZTo6TWVzc2FnZU1hcHBpbmcvdmVyc2lvbjo6MS4yLjE=",
                "metadataURI": "ctype::FlowstepVariant/cname::MessageMapping/version::1.2.1",
                "technicalCapabilities": {}
            },
            {
                "id": "StartEvent_2",
                "name": "Start",
                "componentVersion": "1.0",
                "activityType": "",
                "displayName": "Start Message",
                "ITYPE": "DEFAULT_FLOWSTEP",
                "allAttributes": {},
                "allTableAttributes": {},
                "properties": {
                    "flowstepGeneralTabRequired": "true"
                },
                "hashedMetadataURI": "Y3R5cGU6OkZsb3dzdGVwVmFyaWFudC9jbmFtZTo6TWVzc2FnZVN0YXJ0RXZlbnQvdmVyc2lvbjo6MS4w",
                "metadataURI": "ctype::FlowstepVariant/cname::MessageStartEvent/version::1.0",
                "technicalCapabilities": {}
            },
            {
                "id": "SubProcess_71",
                "name": "Exception Subprocess 1",
                "componentVersion": "1.0",
                "activityType": "ErrorEventSubProcessTemplate",
                "displayName": "Exception Subprocess",
                "ITYPE": "DEFAULT_FLOWSTEP",
                "allAttributes": {},
                "allTableAttributes": {},
                "properties": {
                    "flowstepGeneralTabRequired": "true"
                },
                "hashedMetadataURI": "Y3R5cGU6OkZsb3dzdGVwVmFyaWFudC9jbmFtZTo6RXJyb3JFdmVudFN1YlByb2Nlc3NUZW1wbGF0ZS92ZXJzaW9uOjoxLjAuMg==",
                "metadataURI": "ctype::FlowstepVariant/cname::ErrorEventSubProcessTemplate/version::1.0.2",
                "technicalCapabilities": {}
            },
            {
                "id": "StartEvent_72",
                "name": "Error Start 1",
                "activityType": "",
                "displayName": "Error Start Event",
                "ITYPE": "DEFAULT_FLOWSTEP",
                "allAttributes": {},
                "allTableAttributes": {},
                "properties": {
                    "flowstepGeneralTabRequired": "true"
                },
                "hashedMetadataURI": "Y3R5cGU6OkZsb3dzdGVwVmFyaWFudC9jbmFtZTo6RXJyb3JTdGFydEV2ZW50",
                "metadataURI": "ctype::FlowstepVariant/cname::ErrorStartEvent",
                "technicalCapabilities": {}
            },
            {
                "id": "EndEvent_83",
                "name": "End 1",
                "componentVersion": "1.1",
                "activityType": "",
                "displayName": "End Message",
                "ITYPE": "DEFAULT_FLOWSTEP",
                "allAttributes": {},
                "allTableAttributes": {},
                "properties": {
                    "flowstepGeneralTabRequired": "true"
                },
                "hashedMetadataURI": "Y3R5cGU6OkZsb3dzdGVwVmFyaWFudC9jbmFtZTo6TWVzc2FnZUVuZEV2ZW50L3ZlcnNpb246OjEuMS4w",
                "metadataURI": "ctype::FlowstepVariant/cname::MessageEndEvent/version::1.1.0",
                "technicalCapabilities": {}
            },
            {
                "id": "CallActivity_119",
                "name": "Error Response",
                "componentVersion": "1.5",
                "activityType": "Enricher",
                "displayName": "Content Modifier",
                "ITYPE": "DEFAULT_FLOWSTEP",
                "allAttributes": {
                    "bodyType": {
                        "value": "expression",
                        "defaultValue": "",
                        "key": "",
                        "isPersisted": true
                    },
                    "wrapContent": {
                        "value": "{\n\"Exception\":{\n\"Message\": \"${exception.message}\",\n\"Status\":\"Failed in Cloud Integration iFlow\"\n}\n}",
                        "defaultValue": "",
                        "key": "",
                        "isPersisted": true
                    }
                },
                "allTableAttributes": {
                    "propertyTable": {
                        "value": [],
                        "isPersisted": true
                    },
                    "headerTable": {
                        "value": [
                            {
                                "Action": {
                                    "value": "Create",
                                    "defaultValue": "",
                                    "key": ""
                                },
                                "Type": {
                                    "value": "constant",
                                    "defaultValue": "",
                                    "key": ""
                                },
                                "Value": {
                                    "value": "application/json",
                                    "defaultValue": "",
                                    "key": ""
                                },
                                "Default": {
                                    "value": "",
                                    "defaultValue": "",
                                    "key": ""
                                },
                                "Name": {
                                    "value": "Content-Type",
                                    "defaultValue": "",
                                    "key": ""
                                },
                                "Datatype": {
                                    "value": "",
                                    "defaultValue": "",
                                    "key": ""
                                }
                            },
                            {
                                "Action": {
                                    "value": "Create",
                                    "defaultValue": "",
                                    "key": ""
                                },
                                "Type": {
                                    "value": "constant",
                                    "defaultValue": "",
                                    "key": ""
                                },
                                "Value": {
                                    "value": "200",
                                    "defaultValue": "",
                                    "key": ""
                                },
                                "Default": {
                                    "value": "",
                                    "defaultValue": "",
                                    "key": ""
                                },
                                "Name": {
                                    "value": "CamelHttpResponseCode",
                                    "defaultValue": "",
                                    "key": ""
                                },
                                "Datatype": {
                                    "value": "",
                                    "defaultValue": "",
                                    "key": ""
                                }
                            }
                        ],
                        "isPersisted": true
                    }
                },
                "properties": {
                    "flowstepGeneralTabRequired": "true"
                },
                "hashedMetadataURI": "Y3R5cGU6OkZsb3dzdGVwVmFyaWFudC9jbmFtZTo6RW5yaWNoZXIvdmVyc2lvbjo6MS41LjA=",
                "metadataURI": "ctype::FlowstepVariant/cname::Enricher/version::1.5.0",
                "technicalCapabilities": {}
            },
            {
                "id": "CallActivity_11",
                "name": "Downpayment Request Mapping",
                "componentVersion": "1.2",
                "activityType": "MessageMapping",
                "displayName": "Message Mapping",
                "ITYPE": "DEFAULT_FLOWSTEP",
                "allAttributes": {
                    "mappinguri": {
                        "value": "dir://mmap/src/main/resources/mapping/Workflow_to_S4Hana.mmap",
                        "defaultValue": "",
                        "key": "",
                        "isPersisted": true
                    },
                    "mappingname": {
                        "value": "Workflow_to_S4Hana",
                        "defaultValue": "",
                        "key": "",
                        "isPersisted": true
                    },
                    "mappingpath": {
                        "value": "/Workflow_to_S4Hana.mmap",
                        "defaultValue": "",
                        "key": "",
                        "isPersisted": true
                    },
                    "messageMappingBundleId": {
                        "value": "",
                        "defaultValue": "",
                        "key": "",
                        "isPersisted": true
                    }
                },
                "allTableAttributes": {},
                "properties": {
                    "flowstepGeneralTabRequired": "true"
                },
                "hashedMetadataURI": "Y3R5cGU6OkZsb3dzdGVwVmFyaWFudC9jbmFtZTo6TWVzc2FnZU1hcHBpbmcvdmVyc2lvbjo6MS4yLjE=",
                "metadataURI": "ctype::FlowstepVariant/cname::MessageMapping/version::1.2.1",
                "technicalCapabilities": {}
            }
        ],
        "listOfDefaultProcessModel": [
            {
                "id": "Process_1",
                "name": "Integration Process",
                "componentVersion": "1.1",
                "displayName": "Integration Process",
                "ITYPE": "DEFAULT_PROCESS",
                "allAttributes": {
                    "transactionTimeout": {
                        "value": "30",
                        "defaultValue": "",
                        "key": "",
                        "isPersisted": true
                    },
                    "transactionalHandling": {
                        "value": "Required",
                        "defaultValue": "",
                        "key": "",
                        "isPersisted": true
                    }
                },
                "allTableAttributes": {},
                "properties": {
                    "flowstepGeneralTabRequired": "true"
                },
                "hashedMetadataURI": "Y3R5cGU6OkZsb3dFbGVtZW50VmFyaWFudC9jbmFtZTo6SW50ZWdyYXRpb25Qcm9jZXNzL3ZlcnNpb246OjEuMS4z",
                "metadataURI": "ctype::FlowElementVariant/cname::IntegrationProcess/version::1.1.3",
                "technicalCapabilities": {
                    "$profile.isCapabilitySupported(com.sap.it.capability.technical:cp.jms.messaging.service)": "true"
                }
            }
        ],
        "manifestContent": {
            "SAP-ArtifactTrait": "",
            "SAP-RuntimeProfileName": "Cloud Integration",
            "SAP-ContentMode": "ConfigureOnly",
            "Manifest-Version": "1.0",
            "Origin-Bundle-Version": "1.1.0",
            "SAP-BundleType": "IntegrationFlow",
            "SAP-RuntimeProfile": "iflmap",
            "Bundle-Name": "Supplier Down Payment Request Creation and Confirmation",
            "Origin-ModifiedDate": "1667892825966",
            "Origin-Bundle-SymbolicName": "Supplier_Downpayment_Request_Creation_and_Confirmation",
            "Import-Package": "com.sap.esb.application.services.cxf.interceptor,com.sap.esb.security,com.sap.it.op.agent.api,com.sap.it.op.agent.collector.camel,com.sap.it.op.agent.collector.cxf,com.sap.it.op.agent.mpl,javax.jms,javax.jws,javax.wsdl,javax.xml.bind.annotation,javax.xml.namespace,javax.xml.ws,org.apache.camel;version=\"2.8\",org.apache.camel.builder;version=\"2.8\",org.apache.camel.builder.xml;version=\"2.8\",org.apache.camel.component.cxf,org.apache.camel.model;version=\"2.8\",org.apache.camel.processor;version=\"2.8\",org.apache.camel.processor.aggregate;version=\"2.8\",org.apache.camel.spring.spi;version=\"2.8\",org.apache.commons.logging,org.apache.cxf.binding,org.apache.cxf.binding.soap,org.apache.cxf.binding.soap.spring,org.apache.cxf.bus,org.apache.cxf.bus.resource,org.apache.cxf.bus.spring,org.apache.cxf.buslifecycle,org.apache.cxf.catalog,org.apache.cxf.configuration.jsse;version=\"2.5\",org.apache.cxf.configuration.spring,org.apache.cxf.endpoint,org.apache.cxf.headers,org.apache.cxf.interceptor,org.apache.cxf.management.counters;version=\"2.5\",org.apache.cxf.message,org.apache.cxf.phase,org.apache.cxf.resource,org.apache.cxf.service.factory,org.apache.cxf.service.model,org.apache.cxf.transport,org.apache.cxf.transport.common.gzip,org.apache.cxf.transport.http,org.apache.cxf.transport.http.policy,org.apache.cxf.workqueue,org.apache.cxf.ws.rm.persistence,org.apache.cxf.wsdl11,org.osgi.framework;version=\"1.6.0\",org.slf4j;version=\"1.6\",org.springframework.beans.factory.config;version=\"3.0\",com.sap.esb.camel.security.cms,org.apache.camel.spi,com.sap.esb.webservice.audit.log,com.sap.esb.camel.endpoint.configurator.api,com.sap.esb.camel.jdbc.idempotency.reorg,javax.sql,org.apache.camel.processor.idempotent.jdbc,org.osgi.service.blueprint;version=\"[1.0.0,2.0.0)\"",
            "Origin-Bundle-Name": "Supplier Down Payment Request Creation and Confirmation",
            "Bundle-ManifestVersion": "2",
            "Bundle-SymbolicName": "Supplier_Downpayment_Request_Creation_and_Confirmation",
            "Bundle-Version": "1.1.0",
            "WorkspaceProfile": "iflmap",
            "SAP-NodeType": "IFLMAP",
            "Import-Service": "com.sap.esb.webservice.audit.log.AuditLogger,com.sap.esb.security.KeyManagerFactory;multiple:=false,com.sap.esb.security.TrustManagerFactory;multiple:=false,javax.sql.DataSource;multiple:=false;filter=\"(dataSourceName=default)\",org.apache.cxf.ws.rm.persistence.RMStore;multiple:=false,com.sap.esb.camel.security.cms.SignatureSplitter;multiple:=false"
        },
        "isModelRefreshedForMigration": false,
        "listOfflowStepExternalizedProps": [
            {
                "value": "None",
                "defaultValue": "None",
                "key": "SessionReuse",
                "additionalMetadata": {
                    "isCombobox": "true"
                }
            }
        ]
    },
    "editActionModel": {
        "actionsNotAllowed": "NONE",
        "reason": ""
    },
    "listOfExternalizedPropertiesModel": [
        {
            "propertyObj": {
                "value": "default",
                "defaultValue": "default",
                "key": "proxy",
                "additionalMetadata": {
                    "isCombobox": "true"
                },
                "dataType": "xsd:string"
            },
            "listOfReferences": [
                {
                    "name": "SOAP",
                    "id": "MessageFlow_109",
                    "IType": "DEFAULT_CHANNEL",
                    "refCount": 1
                }
            ],
            "isTable": false
        },
        {
            "propertyObj": {
                "value": "Basic",
                "defaultValue": "Basic",
                "key": "S4Authentication",
                "additionalMetadata": {
                    "isCombobox": "true"
                },
                "dataType": "xsd:string"
            },
            "listOfReferences": [
                {
                    "name": "SOAP",
                    "id": "MessageFlow_109",
                    "IType": "DEFAULT_CHANNEL",
                    "refCount": 1
                }
            ],
            "isTable": false
        },
        {
            "propertyObj": {
                "value": "https://s4hana.api.host",
                "defaultValue": "https://s4hana.api.host",
                "key": "S4Hostname",
                "dataType": "xsd:string"
            },
            "listOfReferences": [
                {
                    "name": "SOAP",
                    "id": "MessageFlow_109",
                    "IType": "DEFAULT_CHANNEL",
                    "refCount": 1
                }
            ],
            "isTable": false
        },
        {
            "propertyObj": {
                "value": "40",
                "defaultValue": "40",
                "key": "BodySize",
                "dataType": "xsd:integer"
            },
            "listOfReferences": [
                {
                    "name": "HTTPS",
                    "id": "MessageFlow_4",
                    "IType": "DEFAULT_CHANNEL",
                    "refCount": 1
                }
            ],
            "isTable": false
        },
        {
            "propertyObj": {
                "value": "60000",
                "defaultValue": "60000",
                "key": "Timeout",
                "dataType": "xsd:integer"
            },
            "listOfReferences": [
                {
                    "name": "SOAP",
                    "id": "MessageFlow_109",
                    "IType": "DEFAULT_CHANNEL",
                    "refCount": 1
                }
            ],
            "isTable": false
        },
        {
            "propertyObj": {
                "value": "ESBMessaging.send",
                "defaultValue": "ESBMessaging.send",
                "key": "UserRole",
                "dataType": "xsd:string"
            },
            "listOfReferences": [
                {
                    "name": "HTTPS",
                    "id": "MessageFlow_4",
                    "IType": "DEFAULT_CHANNEL",
                    "refCount": 1
                }
            ],
            "isTable": false
        },
        {
            "propertyObj": {
                "value": "None",
                "defaultValue": "None",
                "key": "SessionReuse",
                "additionalMetadata": {
                    "isCombobox": "true"
                },
                "dataType": "xsd:string"
            },
            "listOfReferences": [
                {
                    "id": "Collobaration_1",
                    "IType": "DEFAULT_INTEGRATION_FLOW",
                    "displayName": "Integration Flow",
                    "refCount": 1
                }
            ],
            "isTable": false
        },
        {
            "propertyObj": {
                "value": "S4HANA",
                "defaultValue": "S4HANA",
                "key": "S4Credential",
                "dataType": "xsd:string"
            },
            "listOfReferences": [
                {
                    "name": "SOAP",
                    "id": "MessageFlow_109",
                    "IType": "DEFAULT_CHANNEL",
                    "refCount": 1
                }
            ],
            "isTable": false
        },
        {
            "propertyObj": {
                "value": "0",
                "defaultValue": "0",
                "key": "CSRF",
                "additionalMetadata": {
                    "isCombobox": "false"
                },
                "dataType": "xsd:boolean"
            },
            "listOfReferences": [
                {
                    "name": "HTTPS",
                    "id": "MessageFlow_4",
                    "IType": "DEFAULT_CHANNEL",
                    "refCount": 1
                }
            ],
            "isTable": false
        }
    ],
    "galileiModel": {
        "iflowName": "Non PO Downpayment Request Creation",
        "isDirty": false,
        "model": {
            "diagrams": {
                "Diagram": {}
            },
            "participants": {
                "Participant_108": {},
                "Participant_Process_1": {},
                "Participant_1": {}
            },
            "messageFlows": {
                "MessageFlow_109": {},
                "MessageFlow_4": {}
            },
            "id": "Model",
            "classDefinition": "sap.bpm.modelling.Model"
        },
        "diagram": {
            "symbols": {
                "BPMNShape_Participant_108": {},
                "BPMNShape_Participant_1": {},
                "BPMNShape_Participant_Process_1": {},
                "BPMNEdge_MessageFlow_109": {},
                "BPMNEdge_MessageFlow_4": {}
            },
            "id": "Diagram",
            "classDefinition": "sap.bpm.modelling.ui.Diagram"
        },
        "domainElements": {
            "MessageFlow_109": {
                "name": "SOAP",
                "customData": {
                    "type": "Connection",
                    "flavor": "message",
                    "displayName": "SOAP"
                },
                "id": "MessageFlow_109",
                "classDefinition": "sap.bpm.modelling.MessageFlow"
            },
            "StartEvent_72": {
                "eventType": "error",
                "name": "Error Start 1",
                "parentId": "SubProcess_71",
                "customData": {
                    "type": "Event",
                    "flavor": "errorStart",
                    "displayName": "Error Start Event"
                },
                "id": "StartEvent_72",
                "classDefinition": "sap.bpm.modelling.StartEvent"
            },
            "EndEvent_0": {
                "eventType": "message",
                "name": "End 2",
                "parentId": "Process_1",
                "customData": {
                    "type": "Event",
                    "flavor": "intermediatethrow",
                    "displayName": "End Message"
                },
                "id": "EndEvent_0",
                "classDefinition": "sap.bpm.modelling.EndEvent"
            },
            "MessageFlow_4": {
                "name": "HTTPS",
                "customData": {
                    "type": "Connection",
                    "flavor": "message",
                    "displayName": "HTTPS"
                },
                "id": "MessageFlow_4",
                "classDefinition": "sap.bpm.modelling.MessageFlow"
            },
            "EndEvent_83": {
                "eventType": "message",
                "name": "End 1",
                "parentId": "SubProcess_71",
                "customData": {
                    "type": "Event",
                    "flavor": "intermediatethrow",
                    "displayName": "End Message"
                },
                "id": "EndEvent_83",
                "classDefinition": "sap.bpm.modelling.EndEvent"
            },
            "CallActivity_119": {
                "name": "Error Response",
                "parentId": "SubProcess_71",
                "customData": {
                    "type": "Activity",
                    "flavor": "Enricher",
                    "displayName": "Content Modifier"
                },
                "id": "CallActivity_119",
                "classDefinition": "sap.bpm.modelling.CallActivity"
            },
            "CallActivity_113": {
                "name": "Set Content-type",
                "parentId": "Process_1",
                "customData": {
                    "type": "Activity",
                    "flavor": "Enricher",
                    "displayName": "Content Modifier"
                },
                "id": "CallActivity_113",
                "classDefinition": "sap.bpm.modelling.CallActivity"
            },
            "ServiceTask_105": {
                "name": "DPR Creation&Confirmation Response",
                "parentId": "Process_1",
                "customData": {
                    "type": "Activity",
                    "flavor": "ExternalCall",
                    "displayName": "Request Reply"
                },
                "id": "ServiceTask_105",
                "classDefinition": "sap.bpm.modelling.CallActivity"
            },
            "CallActivity_121": {
                "name": "Downpayment Confirmation",
                "parentId": "Process_1",
                "customData": {
                    "type": "Activity",
                    "flavor": "MessageMapping",
                    "displayName": "Message Mapping"
                },
                "id": "CallActivity_121",
                "classDefinition": "sap.bpm.modelling.CallActivity"
            },
            "Participant_Process_1": {
                "process": "Process_1",
                "subProcesses": {
                    "SubProcess_71": {}
                },
                "events": {
                    "EndEvent_0": {},
                    "StartEvent_2": {}
                },
                "sequenceFlows": {
                    "SequenceFlow_118": {},
                    "SequenceFlow_90": {},
                    "SequenceFlow_122": {},
                    "SequenceFlow_111": {},
                    "SequenceFlow_110": {},
                    "SequenceFlow_116": {},
                    "SequenceFlow_114": {}
                },
                "activities": {
                    "CallActivity_121": {},
                    "CallActivity_11": {},
                    "CallActivity_113": {},
                    "CallActivity_102": {},
                    "CallActivity_8": {},
                    "ServiceTask_105": {}
                },
                "gateways": {},
                "name": "Integration Process",
                "customData": {
                    "type": "Pool",
                    "flavor": "Process",
                    "process": "Process_1"
                },
                "id": "Participant_Process_1",
                "classDefinition": "sap.bpm.modelling.Participant"
            },
            "StartEvent_2": {
                "eventType": "message",
                "name": "Start",
                "parentId": "Process_1",
                "customData": {
                    "type": "Event",
                    "flavor": "intermediatecatch",
                    "displayName": "Start Message"
                },
                "id": "StartEvent_2",
                "classDefinition": "sap.bpm.modelling.StartEvent"
            },
            "CallActivity_11": {
                "name": "Downpayment Request Mapping",
                "parentId": "Process_1",
                "customData": {
                    "type": "Activity",
                    "flavor": "MessageMapping",
                    "displayName": "Message Mapping"
                },
                "id": "CallActivity_11",
                "classDefinition": "sap.bpm.modelling.CallActivity"
            },
            "SubProcess_71": {
                "events": {
                    "StartEvent_72": {},
                    "EndEvent_83": {}
                },
                "sequenceFlows": {
                    "SequenceFlow_120": {},
                    "SequenceFlow_74": {}
                },
                "activities": {
                    "CallActivity_119": {}
                },
                "gateways": {},
                "name": "Exception Subprocess 1",
                "parentId": "Process_1",
                "customData": {
                    "type": "subProcess",
                    "flavor": "ErrorEventSubProcessTemplate",
                    "displayName": "Exception Subprocess"
                },
                "id": "SubProcess_71",
                "classDefinition": "sap.bpm.modelling.SubProcess"
            },
            "SequenceFlow_122": {
                "name": "",
                "customData": {
                    "type": "Connection",
                    "flavor": "none"
                },
                "id": "SequenceFlow_122",
                "classDefinition": "sap.bpm.modelling.SequenceFlow"
            },
            "Participant_1": {
                "subProcesses": {},
                "events": {},
                "sequenceFlows": {},
                "activities": {},
                "gateways": {},
                "name": "SAP_WorkflowManagement",
                "customData": {
                    "type": "Pool",
                    "flavor": "System",
                    "iType": "SENDER"
                },
                "id": "Participant_1",
                "classDefinition": "sap.bpm.modelling.Participant"
            },
            "SequenceFlow_120": {
                "name": "",
                "customData": {
                    "type": "Connection",
                    "flavor": "none"
                },
                "id": "SequenceFlow_120",
                "classDefinition": "sap.bpm.modelling.SequenceFlow"
            },
            "CallActivity_102": {
                "name": "XML to JSON Converter",
                "parentId": "Process_1",
                "customData": {
                    "type": "Activity",
                    "flavor": "XmlToJsonConverter",
                    "displayName": "XML To JSON Converter"
                },
                "id": "CallActivity_102",
                "classDefinition": "sap.bpm.modelling.CallActivity"
            },
            "CallActivity_8": {
                "name": "JSON to XML Converter",
                "parentId": "Process_1",
                "customData": {
                    "type": "Activity",
                    "flavor": "JsonToXmlConverter",
                    "displayName": "JSON To XML Converter"
                },
                "id": "CallActivity_8",
                "classDefinition": "sap.bpm.modelling.CallActivity"
            },
            "SequenceFlow_118": {
                "name": "",
                "customData": {
                    "type": "Connection",
                    "flavor": "none"
                },
                "id": "SequenceFlow_118",
                "classDefinition": "sap.bpm.modelling.SequenceFlow"
            },
            "SequenceFlow_90": {
                "name": "",
                "customData": {
                    "type": "Connection",
                    "flavor": "none"
                },
                "id": "SequenceFlow_90",
                "classDefinition": "sap.bpm.modelling.SequenceFlow"
            },
            "Participant_108": {
                "subProcesses": {},
                "events": {},
                "sequenceFlows": {},
                "activities": {},
                "gateways": {},
                "name": "SAPS4HANA",
                "customData": {
                    "type": "Pool",
                    "flavor": "System",
                    "iType": "RECEIVER"
                },
                "id": "Participant_108",
                "classDefinition": "sap.bpm.modelling.Participant"
            },
            "SequenceFlow_74": {
                "name": "",
                "customData": {
                    "type": "Connection",
                    "flavor": "none"
                },
                "id": "SequenceFlow_74",
                "classDefinition": "sap.bpm.modelling.SequenceFlow"
            },
            "SequenceFlow_111": {
                "name": "",
                "customData": {
                    "type": "Connection",
                    "flavor": "none"
                },
                "id": "SequenceFlow_111",
                "classDefinition": "sap.bpm.modelling.SequenceFlow"
            },
            "SequenceFlow_110": {
                "name": "",
                "customData": {
                    "type": "Connection",
                    "flavor": "none"
                },
                "id": "SequenceFlow_110",
                "classDefinition": "sap.bpm.modelling.SequenceFlow"
            },
            "SequenceFlow_116": {
                "name": "",
                "customData": {
                    "type": "Connection",
                    "flavor": "none"
                },
                "id": "SequenceFlow_116",
                "classDefinition": "sap.bpm.modelling.SequenceFlow"
            },
            "SequenceFlow_114": {
                "name": "",
                "customData": {
                    "type": "Connection",
                    "flavor": "none"
                },
                "id": "SequenceFlow_114",
                "classDefinition": "sap.bpm.modelling.SequenceFlow"
            }
        },
        "diagramElements": {
            "BPMNShape_CallActivity_11": {
                "x": 495.0,
                "y": 138.0,
                "width": 100.0,
                "height": 60.0,
                "tooltip": "Name = Workflow_to_S4Hana\nType = Mapping\n",
                "object": "CallActivity_11",
                "symbols": {},
                "isDirty": false,
                "id": "BPMNShape_CallActivity_11",
                "classDefinition": "sap.bpm.modelling.ui.ActivitySymbol"
            },
            "BPMNShape_EndEvent_83": {
                "x": 1077.0,
                "y": 271.0,
                "width": 0.0,
                "height": 0.0,
                "tooltip": "",
                "object": "EndEvent_83",
                "symbols": {},
                "isDirty": false,
                "id": "BPMNShape_EndEvent_83",
                "classDefinition": "sap.bpm.modelling.ui.EndEventSymbol"
            },
            "BPMNShape_CallActivity_119": {
                "x": 939.0,
                "y": 262.0,
                "width": 100.0,
                "height": 60.0,
                "tooltip": "Modifies incoming message with additional information \n",
                "object": "CallActivity_119",
                "symbols": {},
                "isDirty": false,
                "id": "BPMNShape_CallActivity_119",
                "classDefinition": "sap.bpm.modelling.ui.ActivitySymbol"
            },
            "BPMNShape_Participant_1": {
                "x": 75.0,
                "y": 93.0,
                "width": 100.0,
                "height": 140.0,
                "tooltip": "",
                "object": "Participant_1",
                "symbols": {},
                "isDirty": false,
                "id": "BPMNShape_Participant_1",
                "classDefinition": "sap.bpm.modelling.ui.ParticipantSymbol"
            },
            "BPMNShape_StartEvent_72": {
                "x": 872.0,
                "y": 272.0,
                "width": 0.0,
                "height": 0.0,
                "tooltip": "",
                "object": "StartEvent_72",
                "symbols": {},
                "isDirty": false,
                "id": "BPMNShape_StartEvent_72",
                "classDefinition": "sap.bpm.modelling.ui.StartEventSymbol"
            },
            "BPMNShape_EndEvent_0": {
                "x": 1162.0,
                "y": 147.0,
                "width": 0.0,
                "height": 0.0,
                "tooltip": "",
                "object": "EndEvent_0",
                "symbols": {},
                "isDirty": false,
                "id": "BPMNShape_EndEvent_0",
                "classDefinition": "sap.bpm.modelling.ui.EndEventSymbol"
            },
            "BPMNShape_Participant_108": {
                "x": 638.0,
                "y": 464.0,
                "width": 100.0,
                "height": 140.0,
                "tooltip": "",
                "object": "Participant_108",
                "symbols": {},
                "isDirty": false,
                "id": "BPMNShape_Participant_108",
                "classDefinition": "sap.bpm.modelling.ui.ParticipantSymbol"
            },
            "BPMNShape_CallActivity_8": {
                "x": 351.0,
                "y": 138.0,
                "width": 100.0,
                "height": 60.0,
                "tooltip": "",
                "object": "CallActivity_8",
                "symbols": {},
                "isDirty": false,
                "id": "BPMNShape_CallActivity_8",
                "classDefinition": "sap.bpm.modelling.ui.ActivitySymbol"
            },
            "BPMNShape_StartEvent_2": {
                "x": 276.0,
                "y": 147.0,
                "width": 0.0,
                "height": 0.0,
                "tooltip": "",
                "object": "StartEvent_2",
                "symbols": {},
                "isDirty": false,
                "id": "BPMNShape_StartEvent_2",
                "classDefinition": "sap.bpm.modelling.ui.StartEventSymbol"
            },
            "BPMNShape_SubProcess_71": {
                "x": 787.0,
                "y": 227.0,
                "width": 384.0,
                "height": 141.0,
                "tooltip": "",
                "object": "SubProcess_71",
                "symbols": {
                    "BPMNShape_CallActivity_119": {},
                    "BPMNShape_EndEvent_83": {},
                    "BPMNEdge_SequenceFlow_120": {},
                    "BPMNEdge_SequenceFlow_74": {},
                    "BPMNShape_StartEvent_72": {}
                },
                "isDirty": false,
                "id": "BPMNShape_SubProcess_71",
                "classDefinition": "sap.bpm.modelling.ui.SubProcessSymbol"
            },
            "BPMNShape_Participant_Process_1": {
                "x": 224.0,
                "y": 74.0,
                "width": 1054.0,
                "height": 326.0,
                "tooltip": "",
                "object": "Participant_Process_1",
                "symbols": {
                    "BPMNEdge_SequenceFlow_90": {},
                    "BPMNShape_CallActivity_11": {},
                    "BPMNShape_EndEvent_0": {},
                    "BPMNShape_CallActivity_8": {},
                    "BPMNShape_StartEvent_2": {},
                    "BPMNEdge_SequenceFlow_116": {},
                    "BPMNEdge_SequenceFlow_118": {},
                    "BPMNEdge_SequenceFlow_122": {},
                    "BPMNEdge_SequenceFlow_111": {},
                    "BPMNShape_SubProcess_71": {},
                    "BPMNShape_CallActivity_113": {},
                    "BPMNShape_CallActivity_102": {},
                    "BPMNEdge_SequenceFlow_114": {},
                    "BPMNShape_ServiceTask_105": {},
                    "BPMNShape_CallActivity_121": {},
                    "BPMNEdge_SequenceFlow_110": {}
                },
                "isDirty": false,
                "id": "BPMNShape_Participant_Process_1",
                "classDefinition": "sap.bpm.modelling.ui.ParticipantSymbol"
            },
            "BPMNShape_CallActivity_102": {
                "x": 889.0,
                "y": 133.0,
                "width": 100.0,
                "height": 60.0,
                "tooltip": "",
                "object": "CallActivity_102",
                "symbols": {},
                "isDirty": false,
                "id": "BPMNShape_CallActivity_102",
                "classDefinition": "sap.bpm.modelling.ui.ActivitySymbol"
            },
            "BPMNShape_CallActivity_113": {
                "x": 1026.0,
                "y": 133.0,
                "width": 100.0,
                "height": 60.0,
                "tooltip": "Modifies incoming message with additional information \n",
                "object": "CallActivity_113",
                "symbols": {},
                "isDirty": false,
                "id": "BPMNShape_CallActivity_113",
                "classDefinition": "sap.bpm.modelling.ui.ActivitySymbol"
            },
            "BPMNShape_ServiceTask_105": {
                "x": 638.0,
                "y": 138.0,
                "width": 100.0,
                "height": 60.0,
                "tooltip": "",
                "object": "ServiceTask_105",
                "symbols": {},
                "isDirty": false,
                "id": "BPMNShape_ServiceTask_105",
                "classDefinition": "sap.bpm.modelling.ui.ActivitySymbol"
            },
            "BPMNShape_CallActivity_121": {
                "x": 765.0,
                "y": 133.0,
                "width": 100.0,
                "height": 60.0,
                "tooltip": "Name = MM_JournalEntryConfirmation\nType = Mapping\n",
                "object": "CallActivity_121",
                "symbols": {},
                "isDirty": false,
                "id": "BPMNShape_CallActivity_121",
                "classDefinition": "sap.bpm.modelling.ui.ActivitySymbol"
            }
        },
        "connectorDiagramElements": {
            "BPMNEdge_SequenceFlow_90": {
                "object": "SequenceFlow_90",
                "sourceSymbol": "BPMNShape_CallActivity_11",
                "targetSymbol": "BPMNShape_ServiceTask_105",
                "tooltip": "",
                "points": "545.0,168.0 688.0,168.0",
                "id": "BPMNEdge_SequenceFlow_90",
                "classDefinition": "sap.bpm.modelling.ui.SequenceFlowSymbol"
            },
            "BPMNEdge_SequenceFlow_116": {
                "object": "SequenceFlow_116",
                "sourceSymbol": "BPMNShape_StartEvent_2",
                "targetSymbol": "BPMNShape_CallActivity_8",
                "tooltip": "",
                "points": "292.0,165.5 401.0,165.5",
                "id": "BPMNEdge_SequenceFlow_116",
                "classDefinition": "sap.bpm.modelling.ui.SequenceFlowSymbol"
            },
            "BPMNEdge_SequenceFlow_118": {
                "object": "SequenceFlow_118",
                "sourceSymbol": "BPMNShape_CallActivity_8",
                "targetSymbol": "BPMNShape_CallActivity_11",
                "tooltip": "",
                "points": "401.0,168.0 545.0,168.0",
                "id": "BPMNEdge_SequenceFlow_118",
                "classDefinition": "sap.bpm.modelling.ui.SequenceFlowSymbol"
            },
            "BPMNEdge_SequenceFlow_111": {
                "object": "SequenceFlow_111",
                "sourceSymbol": "BPMNShape_CallActivity_102",
                "targetSymbol": "BPMNShape_CallActivity_113",
                "tooltip": "",
                "points": "939.0,163.0 1076.0,163.0",
                "id": "BPMNEdge_SequenceFlow_111",
                "classDefinition": "sap.bpm.modelling.ui.SequenceFlowSymbol"
            },
            "BPMNEdge_SequenceFlow_122": {
                "object": "SequenceFlow_122",
                "sourceSymbol": "BPMNShape_CallActivity_121",
                "targetSymbol": "BPMNShape_CallActivity_102",
                "tooltip": "",
                "points": "815.0,163.0 939.0,163.0",
                "id": "BPMNEdge_SequenceFlow_122",
                "classDefinition": "sap.bpm.modelling.ui.SequenceFlowSymbol"
            },
            "BPMNEdge_SequenceFlow_114": {
                "object": "SequenceFlow_114",
                "sourceSymbol": "BPMNShape_CallActivity_113",
                "targetSymbol": "BPMNShape_EndEvent_0",
                "tooltip": "",
                "points": "1076.0,163.0 1178.0,163.0",
                "id": "BPMNEdge_SequenceFlow_114",
                "classDefinition": "sap.bpm.modelling.ui.SequenceFlowSymbol"
            },
            "BPMNEdge_SequenceFlow_120": {
                "object": "SequenceFlow_120",
                "sourceSymbol": "BPMNShape_CallActivity_119",
                "targetSymbol": "BPMNShape_EndEvent_83",
                "tooltip": "",
                "points": "989.0,289.5 1093.0,289.5",
                "id": "BPMNEdge_SequenceFlow_120",
                "classDefinition": "sap.bpm.modelling.ui.SequenceFlowSymbol"
            },
            "BPMNEdge_SequenceFlow_74": {
                "object": "SequenceFlow_74",
                "sourceSymbol": "BPMNShape_StartEvent_72",
                "targetSymbol": "BPMNShape_CallActivity_119",
                "tooltip": "",
                "points": "888.0,290.0 989.0,290.0",
                "id": "BPMNEdge_SequenceFlow_74",
                "classDefinition": "sap.bpm.modelling.ui.SequenceFlowSymbol"
            },
            "BPMNEdge_SequenceFlow_110": {
                "object": "SequenceFlow_110",
                "sourceSymbol": "BPMNShape_ServiceTask_105",
                "targetSymbol": "BPMNShape_CallActivity_121",
                "tooltip": "",
                "points": "688.0,165.5 815.0,165.5",
                "id": "BPMNEdge_SequenceFlow_110",
                "classDefinition": "sap.bpm.modelling.ui.SequenceFlowSymbol"
            },
            "BPMNEdge_MessageFlow_4": {
                "object": "MessageFlow_4",
                "sourceSymbol": "BPMNShape_Participant_1",
                "targetSymbol": "BPMNShape_StartEvent_2",
                "tooltip": "Name = HTTPS\nAdapter Type = HTTPS\nTransport Protocol =HTTPS\nMessage Protocol = None\n",
                "id": "BPMNEdge_MessageFlow_4",
                "classDefinition": "sap.bpm.modelling.ui.MessageFlowSymbol"
            },
            "BPMNEdge_MessageFlow_109": {
                "object": "MessageFlow_109",
                "sourceSymbol": "BPMNShape_ServiceTask_105",
                "targetSymbol": "BPMNShape_Participant_108",
                "tooltip": "Name = SOAP\nAdapter Type = SOAP\nTransport Protocol = HTTPS\nMessage Protocol = SOAP 1.x\n",
                "id": "BPMNEdge_MessageFlow_109",
                "classDefinition": "sap.bpm.modelling.ui.MessageFlowSymbol"
            }
        },
        "deletedShapes": [],
        "deletedConnectors": []
    }
}